LICENSE
README.md
setup.py
SimpleAxel_Auth.egg-info/PKG-INFO
SimpleAxel_Auth.egg-info/SOURCES.txt
SimpleAxel_Auth.egg-info/dependency_links.txt
SimpleAxel_Auth.egg-info/top_level.txt
auth/__init__.py
auth/main.py